package datamining;

public class Cas {

    private int Occurence;
    private String nom;

    public Cas() {
        // <editor-fold defaultstate="collapsed" desc="Compiled Code">
        /* 0: aload_0
         * 1: invokespecial java/lang/Object."<init>":()V
         * 4: aload_0
         * 5: iconst_0
         * 6: putfield      datamining/Cas.Occurence:I
         * 9: return
         *  */
        // </editor-fold>
    }

    public int getOccurence() {
        // <editor-fold defaultstate="collapsed" desc="Compiled Code">
        /* 0: aload_0
         * 1: getfield      datamining/Cas.Occurence:I
         * 4: ireturn
         *  */
        // </editor-fold>
    }

    public void setOccurence(int occurence) {
        // <editor-fold defaultstate="collapsed" desc="Compiled Code">
        /* 0: aload_0
         * 1: iload_1
         * 2: putfield      datamining/Cas.Occurence:I
         * 5: return
         *  */
        // </editor-fold>
    }

    public String getNom() {
        // <editor-fold defaultstate="collapsed" desc="Compiled Code">
        /* 0: aload_0
         * 1: getfield      datamining/Cas.nom:Ljava/lang/String;
         * 4: areturn
         *  */
        // </editor-fold>
    }

    public void setNom(String nom) {
        // <editor-fold defaultstate="collapsed" desc="Compiled Code">
        /* 0: aload_0
         * 1: aload_1
         * 2: putfield      datamining/Cas.nom:Ljava/lang/String;
         * 5: return
         *  */
        // </editor-fold>
    }
}
