package datamining;

public class Condition {

    private int column;
    private String nom;

    public int getColumn() {
        // <editor-fold defaultstate="collapsed" desc="Compiled Code">
        /* 0: aload_0
         * 1: getfield      datamining/Condition.column:I
         * 4: ireturn
         *  */
        // </editor-fold>
    }

    public void setColumn(int column) {
        // <editor-fold defaultstate="collapsed" desc="Compiled Code">
        /* 0: aload_0
         * 1: iload_1
         * 2: putfield      datamining/Condition.column:I
         * 5: return
         *  */
        // </editor-fold>
    }

    public String getNom() {
        // <editor-fold defaultstate="collapsed" desc="Compiled Code">
        /* 0: aload_0
         * 1: getfield      datamining/Condition.nom:Ljava/lang/String;
         * 4: areturn
         *  */
        // </editor-fold>
    }

    public void setNom(String nom) {
        // <editor-fold defaultstate="collapsed" desc="Compiled Code">
        /* 0: aload_0
         * 1: aload_1
         * 2: putfield      datamining/Condition.nom:Ljava/lang/String;
         * 5: return
         *  */
        // </editor-fold>
    }

    public Condition() {
        // <editor-fold defaultstate="collapsed" desc="Compiled Code">
        /* 0: aload_0
         * 1: invokespecial java/lang/Object."<init>":()V
         * 4: return
         *  */
        // </editor-fold>
    }
}
